{
  "project_info": {
    "project_number": "763884597283",
    "firebase_url": "https://sportsfete19-f7729.firebaseio.com",
    "project_id": "sportsfete19-f7729",
    "storage_bucket": "sportsfete19-f7729.appspot.com"
  },
  "client": [
    {
      "client_info": {
        "mobilesdk_app_id": "1:763884597283:android:d550bb74b63cb957c28196",
        "android_client_info": {
          "package_name": "com.example.aravind.sportsfeteadmin"
        }
      },
      "oauth_client": [
        {
          "client_id": "763884597283-on8i5dvvneu5cg344jdbdj1svfc409nk.apps.googleusercontent.com",
          "client_type": 3
        }
      ],
      "api_key": [
        {
          "current_key": "AIzaSyASDBcf27cfFnffDdCrbMKqNick3wZL3Cw"
        }
      ],
      "services": {
        "appinvite_service": {
          "other_platform_oauth_client": [
            {
              "client_id": "763884597283-on8i5dvvneu5cg344jdbdj1svfc409nk.apps.googleusercontent.com",
              "client_type": 3
            }
          ]
        }
      }
    },
    {
      "client_info": {
        "mobilesdk_app_id": "1:763884597283:android:28ae08ef507780bbc28196",
        "android_client_info": {
          "package_name": "org.spider.sportsfete"
        }
      },
      "oauth_client": [
        {
          "client_id": "763884597283-on8i5dvvneu5cg344jdbdj1svfc409nk.apps.googleusercontent.com",
          "client_type": 3
        }
      ],
      "api_key": [
        {
          "current_key": "AIzaSyASDBcf27cfFnffDdCrbMKqNick3wZL3Cw"
        }
      ],
      "services": {
        "appinvite_service": {
          "other_platform_oauth_client": [
            {
              "client_id": "763884597283-on8i5dvvneu5cg344jdbdj1svfc409nk.apps.googleusercontent.com",
              "client_type": 3
            }
          ]
        }
      }
    }
  ],
  "configuration_version": "1"
}